{
   "Name": "98 Mute",
   "rawData": [
      "98 Mute was an American hardcore punk band from Hermosa Beach, California, United States. They were formed in 1993, and signed to Theologian Records in 1995. Their first, self-titled album was released in 1996, and the band was featured on several skate videos and compilations of Californian punk. The group had toured with bands like The Offspring, Blink-182 and Pennywise. A second album on Theologian followed in 1998 before the group was picked up by Epitaph Records. They released two albums on Epitaph before breaking up in September 2002, shortly after the release of their fourth full-length, After the Fall.\n",
      "98 Mute reunited in 2016.\n"
   ],
   "infobox": {
      "Origin": [
         "Hermosa Beach, California, United States"
      ],
      "Genres": [
         "Hardcore punk"
      ],
      "Years active": [
         "1993â€“2002, 2016"
      ],
      "Labels": [
         "Theologian Records",
         "Epitaph Records"
      ]
   },
   "albums": [
      "98 Mute",
      "Class of 98",
      "Slow Motion Riot",
      "After the Fall"
   ]
}